LICENSE
MANIFEST.in
README.md
requirements.txt
setup.py
postmancli/__init__.py
postmancli/__main__.py
postmancli/core.py
postmancli/main.py
postmancli/metadata.py
postmancli/sendemail.py
postmancli/validation.py
postmancli.egg-info/PKG-INFO
postmancli.egg-info/SOURCES.txt
postmancli.egg-info/dependency_links.txt
postmancli.egg-info/entry_points.txt
postmancli.egg-info/top_level.txt