Metadata-Version: 2.1
Name: postmancli
Version: 0.1.1
Summary: CLI tool for emails sending using SMTP server
Home-page: https://github.com/RDCH106/postman-cli
Author: Rubén de Celis Hernández
Author-email: contact@rdch106.hol.es
License: LGPL v3
Download-URL: https://github.com/RDCH106/postman-cli/archive/v0.1.1.tar.gz
Keywords: cli command-line email-sender
Platform: UNKNOWN
Classifier: Programming Language :: Python
Classifier: Programming Language :: Python :: 2.7
Classifier: Programming Language :: Python :: 3.4
Classifier: Programming Language :: Python :: 3.5
Classifier: Programming Language :: Python :: 3.6
Classifier: Programming Language :: Python :: 3.7
Classifier: Programming Language :: Python :: 3.8
